[
  {
    "title": "OpenCASCADE",
    "image": {
      "url": "images/features/occt_logo.png",
      "width": 80,
      "height": 80
    }
  },
  {
    "title": "C/C++",
    "image": {
      "url": "images/features/cpp.png",
      "width": 80,
      "height": 80
    }
  },
  {
    "title": "C3D",
    "image": {
      "url": "images/features/c3d.jpg",
      "width": 140,
      "height": 80
    }
  },
  {
    "title": "CMake",
    "image": {
      "url": "images/features/cmake.webp",
      "width": 80,
      "height": 80
    }
  },
  {
    "title": "vcpkg",
    "image": {
      "url": "images/features/vcpkg.png",
      "width": 80,
      "height": 80
    }
  },
  {
    "title": "Docker",
    "image": {
      "url": "images/features/docker.svg",
      "width": 80,
      "height": 80
    }
  },
  {
    "title": "Qt",
    "image": {
      "url": "images/features/qt.svg",
      "width": 80,
      "height": 80
    }
  },
  {
    "title": "Google Testing",
    "image": {
      "url": "images/features/googletest.png",
      "width": 80,
      "height": 80
    }
  },
  {
    "title": "OpenGL",
    "image": {
      "url": "images/features/opengl.svg",
      "width": 80,
      "height": 80
    }
  },
  {
    "title": "Vulkan",
    "image": {
      "url": "images/features/vulkan.svg",
      "width": 80,
      "height": 80
    }
  },
  {
    "title": "Linux",
    "image": {
      "url": "images/features/linux.png",
      "width": 80,
      "height": 80
    }
  },
  {
    "title": "Git",
    "image": {
      "url": "images/features/git-logo.svg",
      "width": 80,
      "height": 80
    }
  },
  {
    "title": "OpenMP",
    "image": {
      "url": "images/features/openmp.png",
      "width": 80,
      "height": 80
    }
  },
  {
    "title": "wxWidgets",
    "image": {
      "url": "images/features/wxwidgets.svg",
      "width": 80,
      "height": 80
    }
  },
  {
    "title": "MPI",
    "image": {
      "url": "images/features/mpi.jpg",
      "width": 80,
      "height": 80
    }
  }
]
